{"api_bayesianupdating.md":"QAr1BSy8","api_inputs.md":"dA38rs7l","api_models.md":"1LMuLzkN","api_polyharmonicspline.md":"CnYrTA2n","api_polynomialchaos.md":"DGkz-pW_","api_psd.md":"CSNDsfgg","api_reliability.md":"D3WjV5TJ","api_responsesurface.md":"Df73Nq87","api_simulations.md":"DCR3JY4R","api_slurm.md":"Bca30dV9","api_spectralrepresentation.md":"BJpw0kC2","benchmarks_subset.md":"DnLokr_a","examples_bayesianupdating.md":"BIsI50Sd","examples_dynamics.md":"DM5SZZLz","examples_external.md":"DklxfZUl","examples_hpc.md":"DiON_fV3","examples_inputs.md":"C2KAFnqQ","examples_metamodels.md":"CFpb6Lkj","index.md":"CmRQgA10","manual_bayesianupdating.md":"CSoV6f7F","manual_dynamics.md":"DBLmf1Us","manual_gaussianmixture.md":"eqhy7eKJ","manual_gettingstarted.md":"CXHvVeHO","manual_hpc.md":"DK1Z2EyN","manual_introduction.md":"sFuNRI0E","manual_kde.md":"oS8Evw7N","manual_metamodels.md":"D5S6HgGc","manual_parallelisation.md":"DUVQMN8b","manual_reliability.md":"BZKgz0IO","manual_simulations.md":"CKNBvLzQ","references.md":"CLvBJdqN"}
